kaizen_cli/__init__.py
kaizen_cli/cli.py
kaizen_cli/commands/config_commands.py
kaizen_cli/commands/reviewer_commands.py
kaizen_cli/commands/unit_test_commands.py
kaizen_cli/config/default_config.py
kaizen_cli/config/manager.py
kaizen_cli/hooks/prepare-commit-msg
kaizen_cli/hooks/setup.py
kaizen_cli/utils.py
kaizen_cli-0.2.7.dist-info/METADATA
kaizen_cli-0.2.7.dist-info/WHEEL
kaizen_cli-0.2.7.dist-info/entry_points.txt
kaizen_cli-0.2.7.dist-info/RECORD
