Metadata-Version: 2.1
Name: kaizen-cli
Version: 0.2.7
Summary: 
Author: Saurav Panda
Author-email: sgp65@cornell.edu
Requires-Python: >=3.9.0,<4.0.0
Classifier: Programming Language :: Python :: 3
Classifier: Programming Language :: Python :: 3.9
Classifier: Programming Language :: Python :: 3.10
Classifier: Programming Language :: Python :: 3.11
Classifier: Programming Language :: Python :: 3.12
Requires-Dist: click (>=8.1.3,<9.0.0)
Requires-Dist: kaizen-cloudcode (>=0.4.17,<0.5.0)
